Workbook

Sheet Instructions
A1: Portfolio Command — Finance Data Templates
A2: For the historical load of transactions, valuation marks and fund (LP) activity.
A4: How to use these sheets
A5: Fill one row per record. Do not add, remove, rename or reorder columns — the loader matches on header text.
A6: Pink columns are required. Grey columns are optional but load if present.
A7: Row 2 of each sheet is a worked example. Delete it before sending, or leave it — rows marked EXAMPLE are skipped.
A8: Company names do not need to match anything. The loader resolves them against a crosswalk we build first;
A9: anything it cannot match comes back to you on an exceptions list rather than being guessed at.
A11: Conventions
A12: Amounts in whole Canadian dollars, not millions. 8500000, not 8.5.
A13: All amounts positive. Direction is implied by the transaction type — do not use negative numbers for outflows.
A14: Dates as YYYY-MM-DD.
... A38: Questions to the Systems & Data Analyst. Nothing here is fixed; if a column does not fit how you hold the data, say so.

Sheet Company Master
A1: company_name | B1: also_known_as | C1: status | D1: first_investment_date | E1: hq_city | F1: hq_province | G1: notes
A2: EXAMPLE — Fiddlehead Robotics Inc. | B2: Fiddlehead Automation Ltd; FRI | C2: Active | D2: 2018-06-14 | E2: Fredericton | F2: NB | G2: Renamed 2021 after Series A
A62: Column notes
A63: company_name | B63: REQUIRED. The name as it appears in your records. Does not need to match Affinity.
A64: also_known_as | B64: Optional. Former names, trading names, legal name if different. Semicolon-separated. This is the field that prevents duplicate companies.
A65: status | B65: Optional. Active, Exited, Written off, or Dissolved.
A66: first_investment_date | B66: Optional. Approximate is fine if the exact date is not recoverable — flag it in notes.
A67: hq_city | B67: Optional.
A68: hq_province | B68: Optional. Two-letter code. NB drives the mandate split, so this one matters.
A69: notes | B69: Optional. Anything unusual: acquired by another portfolio company, restructured, name changed mid-life, holding company versus operating company.

Sheet Rounds
A1: company_name | B1: round_date | C1: round_label | D1: instrument | E1: our_investment_cad | F1: round_total_cad | G1: nb_other_cad | H1: post_money_cad | I1: ownership_after_pct | J1: lead_investor | K1: source_document | L1: notes
A2: EXAMPLE — Fiddlehead Robotics Inc. | B2: 2021-03-09 | C2: Series A | D2: Preferred Equity | E2: 1500000 | F2: 6200000 | G2: 900000 | H2: 24000000 | I2: 8.4 | J2: East Valley Ventures | K2: /Legal/Fiddlehead/SeriesA/
A62: Column notes
A63: company_name | B63: REQUIRED. Must match a name on the Company Master sheet.
A64: round_date | B64: REQUIRED. Closing date.
A65: round_label | B65: REQUIRED. Seed, Series A, Bridge, and so on. Your naming is fine.
A66: instrument | B66: REQUIRED. SAFE, Convertible Note, Debt-to-Note, Preferred Equity, or Common Equity.
A67: our_investment_cad | B67: REQUIRED. Our cheque into this round, whole dollars. Should equal the sum of the matching Transactions rows.
A68: round_total_cad | B68: Optional. FULL round size, all investors including us. Blank if not recoverable — blank is excluded from the leverage metric, a guess would corrupt it.
A69: nb_other_cad | B69: Optional. Capital from OTHER New Brunswick investors in this round, excluding ours.
A70: post_money_cad | B70: Optional. Blank for SAFEs and notes.
A71: ownership_after_pct | B71: Optional. Our fully-diluted ownership after close. 11.2 means 11.2%.
A72: lead_investor | B72: Optional. 'Us' if we led.
A73: source_document | B73: Optional. SharePoint link or file reference for the closing documents.
A74: notes | B74: Optional.

Sheet Transactions
A1: transaction_date | B1: company_name | C1: transaction_type | D1: amount_cad | E1: round_label | F1: currency | G1: fx_rate_to_cad | H1: source_document | I1: notes
A2: EXAMPLE — 2021-03-09 | B2: Fiddlehead Robotics Inc. | C2: Follow-on | D2: 1500000 | E2: Series A | H2: /Finance/Wires/2021-03-09.pdf
A62: Column notes
A63: transaction_date | B63: REQUIRED. Effective date of the cash movement, not the date it was recorded.
A64: company_name | B64: REQUIRED. Leave blank only for LP fund transactions — those belong on the Fund Cashflows sheet instead.
A65: transaction_type | B65: REQUIRED. One of: Investment, Follow-on, Realization, Write-off. First cheque into a company is Investment; every later cheque is Follow-on.
A66: amount_cad | B66: REQUIRED. Whole dollars, ALWAYS POSITIVE. Direction comes from the type.
A67: round_label | B67: Optional. Which round this cheque belongs to, matching the Rounds sheet. Blank if it does not map to a round.
A68: currency | B68: Optional. Blank means CAD. Only fill if the transaction was settled in another currency.
A69: fx_rate_to_cad | B69: Optional. Only if currency is not CAD. Rate on the transaction date.
A70: source_document | B70: Optional. Wire confirmation, subscription agreement, board resolution — whatever ties the entry to evidence.
A71: notes | B71: Optional. For realizations: what the proceeds were from. Acquisition, secondary, escrow release, dividend.

Sheet Valuation Marks
A1: company_name | B1: effective_date | C1: fmv_cad | D1: method | E1: rationale | F1: prepared_by | G1: completed_date | H1: source_document
A2: EXAMPLE — Fiddlehead Robotics Inc. | B2: 2025-07-31 | C2: 3800000 | D2: Calibrated last round | E2: Series A price held; revenue tracking to plan, no new round since close. | G2: 2025-10-06
A62: Column notes
A63: company_name | B63: REQUIRED. Must match the Company Master sheet.
A64: effective_date | B64: REQUIRED. The date the valuation is AS AT — 31 January or 31 July — not the date the exercise was completed or presented.
A65: fmv_cad | B65: REQUIRED. Our fair market value of the position, whole dollars.
A66: method | B66: REQUIRED. Last round, Revenue multiple, Calibrated last round, Scenario-weighted, Write-off, or Realized.
A67: rationale | B67: REQUIRED. Why this number. One or two sentences is enough. This is the field a board member or auditor reads when they challenge a mark, and it is the single most valuable column on this sheet.
A68: prepared_by | B68: Optional. Name of whoever ran the valuation for that cycle.
A69: completed_date | B69: Optional. When the exercise was actually finished, if known. Lets us show 'as at 31 Jan, booked 12 Apr' rather than implying same-day.
A70: source_document | B70: Optional.

Sheet Fund Investments
A1: fund_name | B1: manager_name | C1: strategy | D1: vintage_year | E1: committed_cad | F1: co_invest_rights | G1: women_senior_gp | H1: next_call_expected | I1: agm_date | J1: ir_contact | K1: rationale | L1: source_document
A2: EXAMPLE — Maritime Growth Fund II | B2: Maritime Capital Partners | C2: Early stage | D2: 2022 | E2: 5000000 | F2: Y | H2: 2026-09-30 | I2: 2026-11-12 | K2: Access to Atlantic deal flow and co-invest rights
A62: Column notes
A63: fund_name | B63: REQUIRED. The LP position — the fund we committed to.
A64: manager_name | B64: REQUIRED. The GP firm.
A65: strategy | B65: Optional. Seed, Early stage, Growth, Sector-specific, Fund of funds.
A66: vintage_year | B66: Optional.
A67: committed_cad | B67: REQUIRED. Total commitment per the subscription agreement, whole dollars.
A68: co_invest_rights | B68: Optional. Y or N.
A69: women_senior_gp | B69: Optional. Y or N. Blank if not known — blank is not the same as N.
A70: next_call_expected | B70: Optional.
A71: agm_date | B71: Optional.
A72: ir_contact | B72: Optional.
A73: rationale | B73: Optional. Why we are in this fund. Strategic reason, not just the financial case.
A74: source_document | B74: Optional. LPA or subscription agreement.

Sheet Fund Cashflows
A1: fund_name | B1: cashflow_date | C1: cashflow_type | D1: amount_cad | E1: notice_reference | F1: notes
A2: EXAMPLE — Maritime Growth Fund II | B2: 2024-02-15 | C2: Capital call | D2: 750000 | E2: MGF2-CC-07
A62: Column notes
A63: fund_name | B63: REQUIRED. Must match the Fund Investments sheet.
A64: cashflow_date | B64: REQUIRED.
A65: cashflow_type | B65: REQUIRED. Capital call, Distribution, or Fee.
A66: amount_cad | B66: REQUIRED. ALWAYS POSITIVE. Do not use negatives for calls — the type carries the direction.
A67: notice_reference | B67: Optional. Call or distribution notice number.
A68: notes | B68: Optional.

Sheet Fund NAV Statements
A1: fund_name | B1: as_of_date | C1: nav_cad | D1: statement_received | E1: source_document
A2: EXAMPLE — Maritime Growth Fund II | B2: 2026-03-31 | C2: 4100000 | D2: 2026-05-22
A62: Column notes
A63: fund_name | B63: REQUIRED. Must match the Fund Investments sheet.
A64: as_of_date | B64: REQUIRED. The date the GP statement is as at.
A65: nav_cad | B65: REQUIRED. Our capital account value per the GP statement.
A66: statement_received | B66: Optional. When it reached us. GP statements typically lag a quarter and we want to show that honestly.
A67: source_document | B67: Optional.

Sheet Control Totals
A1: Control Totals
A2: Fill the 'Your figure' column from your own records before sending a batch. The loader compares against these.
A3: The computed column reads the sheets in this workbook, so you can see a mismatch before we do.
A5: Check | B5: Your figure (from your records) | C5: Computed from this workbook | D5: Difference | E5: Agrees?
A6: Total invested — all Transactions of type Investment | C6: =SUMIF(Transactions!C3:C59,"Investment",Transactions!D3:D59) -> 0 | D6: =IF(B6="","",C6-B6) | E6: =IF(B6="","not yet entered",IF(ROUND(C6-B6,2)=0,"agrees","INVESTIGATE")) -> not yet entered
A7: Total follow-on — all Transactions of type Follow-on | C7: =SUMIF(Transactions!C3:C59,"Follow-on",Transactions!D3:D59) -> 0 | D7: =IF(B7="","",C7-B7) | E7: =IF(B7="","not yet entered",IF(ROUND(C7-B7,2)=0,"agrees","INVESTIGATE")) -> not yet entered
A8: Total realizations | C8: =SUMIF(Transactions!C3:C59,"Realization",Transactions!D3:D59) -> 0 | D8: =IF(B8="","",C8-B8) | E8: =IF(B8="","not yet entered",IF(ROUND(C8-B8,2)=0,"agrees","INVESTIGATE")) -> not yet entered
A9: Total write-offs | C9: =SUMIF(Transactions!C3:C59,"Write-off",Transactions!D3:D59) -> 0 | D9: =IF(B9="","",C9-B9) | E9: =IF(B9="","not yet entered",IF(ROUND(C9-B9,2)=0,"agrees","INVESTIGATE")) -> not yet entered
A10: Our investment across all Rounds | C10: =SUM(Rounds!E3:E59) -> 0 | D10: =IF(B10="","",C10-B10) | E10: =IF(B10="","not yet entered",IF(ROUND(C10-B10,2)=0,"agrees","INVESTIGATE")) -> not yet entered
A11: Number of companies on the Company Master | C11: =COUNTA('Company Master'!A3:A59) -> 0 | D11: =IF(B11="","",C11-B11) | E11: =IF(B11="","not yet entered",IF(ROUND(C11-B11,2)=0,"agrees","INVESTIGATE")) -> not yet entered
A12: Number of valuation marks | C12: =COUNTA('Valuation Marks'!A3:A59) -> 0 | D12: =IF(B12="","",C12-B12) | E12: =IF(B12="","not yet entered",IF(ROUND(C12-B12,2)=0,"agrees","INVESTIGATE")) -> not yet entered
A13: Total FMV across marks in this batch | C13: =SUM('Valuation Marks'!C3:C59) -> 0 | D13: =IF(B13="","",C13-B13) | E13: =IF(B13="","not yet entered",IF(ROUND(C13-B13,2)=0,"agrees","INVESTIGATE")) -> not yet entered
A14: Total committed across LP positions | C14: =SUM('Fund Investments'!E3:E59) -> 0 | D14: =IF(B14="","",C14-B14) | E14: =IF(B14="","not yet entered",IF(ROUND(C14-B14,2)=0,"agrees","INVESTIGATE")) -> not yet entered
A15: Total capital called | C15: =SUMIF('Fund Cashflows'!C3:C59,"Capital call",'Fund Cashflows'!D3:D59) -> 0 | D15: =IF(B15="","",C15-B15) | E15: =IF(B15="","not yet entered",IF(ROUND(C15-B15,2)=0,"agrees","INVESTIGATE")) -> not yet entered
A16: Total LP distributions received | C16: =SUMIF('Fund Cashflows'!C3:C59,"Distribution",'Fund Cashflows'!D3:D59) -> 0 | D16: =IF(B16="","",C16-B16) | E16: =IF(B16="","not yet entered",IF(ROUND(C16-B16,2)=0,"agrees","INVESTIGATE")) -> not yet entered
A19: Anything reading INVESTIGATE gets resolved before the batch is loaded, not after.
A20: A difference is usually a missing row, a duplicated row, or an amount entered in millions rather than dollars.
